collabo/__init__.py
collabo/main.py
collabo/utils.py
collabo-0.2.0.dist-info/LICENSE
collabo-0.2.0.dist-info/METADATA
collabo-0.2.0.dist-info/WHEEL
collabo-0.2.0.dist-info/top_level.txt
collabo-0.2.0.dist-info/RECORD
