Metadata-Version: 2.1
Name: collabo
Version: 0.2.0
Summary: A package for human-algorithm collaborative Bayesian optimization.
Home-page: UNKNOWN
Author: Tom Savage
Author-email: tom.savage@hotmail.com
License: UNKNOWN
Platform: UNKNOWN
Classifier: Programming Language :: Python :: 3
Classifier: License :: OSI Approved :: MIT License
Classifier: Operating System :: OS Independent
Requires-Python: >=3.9
License-File: LICENSE
